instagram_image_uploader/__init__.py
instagram_image_uploader/__main__.py
instagram_image_uploader-0.0.2.dist-info/LICENSE
instagram_image_uploader-0.0.2.dist-info/METADATA
instagram_image_uploader-0.0.2.dist-info/WHEEL
instagram_image_uploader-0.0.2.dist-info/top_level.txt
instagram_image_uploader-0.0.2.dist-info/RECORD
